item_local/__init__.py
item_local/item.py
item_local-0.0.9.dist-info/METADATA
item_local-0.0.9.dist-info/WHEEL
item_local-0.0.9.dist-info/top_level.txt
item_local-0.0.9.dist-info/RECORD
