Metadata-Version: 2.1
Name: item-local
Version: 0.0.9
Home-page: https://github.com/circles-zone/item-local-python-package
Author: Circles
Author-email: info@circles.life
Classifier: Programming Language :: Python :: 3
Classifier: License :: Other/Proprietary License
Classifier: Operating System :: OS Independent
Requires-Dist: logger-local >=0.0.101
